MANIFEST.in
README.md
setup.py
case_studies/__init__.py
case_studies/admin.py
case_studies/app_registry.py
case_studies/feeds.py
case_studies/forms.py
case_studies/managers.py
case_studies/models.py
case_studies/search_indexes.py
case_studies/settings.json
case_studies/signals.py
case_studies/urls.py
case_studies/views.py
case_studies/migrations/0001_initial.py
case_studies/migrations/0002_auto__del_technology__del_field_casestudy_url.py
case_studies/migrations/__init__.py
case_studies/static/css/casestudy-search.css
case_studies/static/css/casestudy.css
case_studies/templates/case_studies/base.html
case_studies/templates/case_studies/meta.html
case_studies/templates/case_studies/options.html
case_studies/templates/case_studies/print-view.html
case_studies/templates/case_studies/search-form.html
case_studies/templates/case_studies/search-result.html
case_studies/templates/case_studies/search.html
case_studies/templates/case_studies/view.html
case_studies/templates/case_studies/admin/change_form.html
case_studies/templates/search/indexes/case_studies/casestudy_text.txt
case_studies/templates/search/indexes/case_studies/image_text.txt
case_studies/templatetags/__init__.py
case_studies/templatetags/case_study_tags.py
tendenci_case_studies.egg-info/PKG-INFO
tendenci_case_studies.egg-info/SOURCES.txt
tendenci_case_studies.egg-info/dependency_links.txt
tendenci_case_studies.egg-info/requires.txt
tendenci_case_studies.egg-info/top_level.txt